scholarSparkObservability/__init__.py
scholarSparkObservability/core.py
scholar_spark_observability-0.8.0.dist-info/LICENSE
scholar_spark_observability-0.8.0.dist-info/METADATA
scholar_spark_observability-0.8.0.dist-info/WHEEL
scholar_spark_observability-0.8.0.dist-info/RECORD
