Metadata-Version: 2.1
Name: scholar-spark-observability
Version: 0.8.0
Summary: A Python package for monitoring and observability in Apache Spark applications
Home-page: https://github.com/Polyhistor/ScholarSparkObservability
Keywords: spark,observability,monitoring,opentelemetry
Author: Pouya Ataei
Author-email: pouya.ataei.7@gmail.com
Requires-Python: >=3.8,<4.0
Classifier: Programming Language :: Python :: 3
Classifier: Programming Language :: Python :: 3.8
Classifier: Programming Language :: Python :: 3.9
Classifier: Programming Language :: Python :: 3.10
Classifier: Programming Language :: Python :: 3.11
Classifier: Programming Language :: Python :: 3.12
Classifier: Programming Language :: Python :: 3.13
Provides-Extra: jaeger
Provides-Extra: zipkin
Requires-Dist: opentelemetry-api (>=1.20.0,<2.0.0)
Requires-Dist: opentelemetry-exporter-jaeger (>=1.20.0,<2.0.0) ; extra == "jaeger"
Requires-Dist: opentelemetry-exporter-otlp (>=1.20.0,<2.0.0)
Requires-Dist: opentelemetry-exporter-otlp-proto-http (>=1.20.0,<2.0.0)
Requires-Dist: opentelemetry-exporter-zipkin (>=1.20.0,<2.0.0) ; extra == "zipkin"
Requires-Dist: opentelemetry-sdk (>=1.20.0,<2.0.0)
Project-URL: Documentation, https://scholar-spark-observability.readthedocs.io
Project-URL: Repository, https://github.com/Polyhistor/ScholarSparkObservability
